fxe/__init__.py
fxe/ai/__init__.py
fxe/ai/evaluator.py
fxe/cli/__init__.py
fxe/core/__init__.py
fxe/data/__init__.py
fxe/tools/__init__.py
fxe/tools/plot.py
fxe/utils/__init__.py
fxe/utils/analysis.py
fxe/utils/notify.py
fxe-0.1.3.dev2.dist-info/METADATA
fxe-0.1.3.dev2.dist-info/WHEEL
fxe-0.1.3.dev2.dist-info/entry_points.txt
fxe-0.1.3.dev2.dist-info/licenses/LICENSE
fxe-0.1.3.dev2.dist-info/RECORD
