Metadata-Version: 2.4
Name: fxe
Version: 0.1.3.dev2
Summary: finlab extension tool
Project-URL: Homepage, https://github.com/juishuyeh/fxe
Author-email: JSYEH <juishuyeh@gmail.com>
License:                                  Apache License
License-File: LICENSE
Classifier: Development Status :: 4 - Beta
Classifier: Intended Audience :: Financial and Insurance Industry
Classifier: License :: OSI Approved :: Apache Software License
Classifier: Operating System :: MacOS
Classifier: Programming Language :: Python :: 3.11
Classifier: Programming Language :: Python :: 3.12
Classifier: Programming Language :: Python :: 3.13
Requires-Python: >=3.11
Requires-Dist: finlab[cli]>=1.2.20
Requires-Dist: matplotlib>=3.10.1
Requires-Dist: plotly>=6.0.0
Requires-Dist: ta-lib>=0.6.0
